Workbook
Name aporte: Simulador!$D$17
Name capital_inicial: Ajustes!$B$7
Name limite_anos: Ajustes!$B$9
Name meses_ano: Ajustes!$B$6
Name momento_aporte: Ajustes!$B$8
Name patrimonio: Simulador!$D$20
Name percentual_sugerido: Ajustes!$B$5
Name perfis: Perfis!$B$25:$B$27
Name qtd_anos: Simulador!$D$18
Name rendimento_carteira: Simulador!$D$13
Name salario: Simulador!$D$12
Name sugestao_investimento: Simulador!$D$14
Name taxa_mensal: Simulador!$D$19
Name tolerancia: Ajustes!$B$10

Sheet Simulador
B3: Simulador de FIIs
B11: Seus dados
B12: Salário mensal | D12: 2000
B13: Taxa mensal de dividendos | D13: 0.006
B14: Sugestão de aporte | D14: =salario*percentual_sugerido -> 600
B16: Sua simulação
B17: Quanto investir por mês? | D17: 200
B18: Prazo em anos | D18: 5
B19: Taxa mensal de acumulação | D19: 0.01079
B20: Patrimônio acumulado | D20: =FV(taxa_mensal,qtd_anos*meses_ano,-aporte,-capital_inicial,momento_aporte) -> 16755.383
B21: Dividendos mensais estimados | D21: =patrimonio*rendimento_carteira -> 100.5323
B23: Prazo | C23: Patrimônio | D23: Dividendo mensal
B24: 2 | C24: =FV(taxa_mensal,$B24*meses_ano,-aporte,-capital_inicial,momento_aporte) -> 5445.5255 | D24: =C24*rendimento_carteira -> 32.673153
B25: 5 | C25: =FV(taxa_mensal,$B25*meses_ano,-aporte,-capital_inicial,momento_aporte) -> 16755.383 | D25: =C25*rendimento_carteira -> 100.5323
B26: 10 | C26: =FV(taxa_mensal,$B26*meses_ano,-aporte,-capital_inicial,momento_aporte) -> 48656.843 | D26: =C26*rendimento_carteira -> 291.94106
B27: 20 | C27: =FV(taxa_mensal,$B27*meses_ano,-aporte,-capital_inicial,momento_aporte) -> 225039.68 | D27: =C27*rendimento_carteira -> 1350.2381
B28: 30 | C28: =FV(taxa_mensal,$B28*meses_ano,-aporte,-capital_inicial,momento_aporte) -> 864433.93 | D28: =C28*rendimento_carteira -> 5186.6036
B29: Quanto foi investido | D29: =capital_inicial+aporte*qtd_anos*meses_ano -> 12000
B30: Rendimentos no período | D30: =D20-D29 -> 4755.3828
B32: Perfil escolhido | C32: Moderado
B33: Aporte mensal | C33: =aporte -> 200
B35: Tipo de FII | C35: Percentual | D35: Aporte por mês
B36: PAPEL | C36: =VLOOKUP($C$32&"-"&B36,Perfis!$A$3:$D$20,4,FALSE) -> 0.32 | D36: =C36*$C$33 -> 64
B37: TIJOLO | C37: =VLOOKUP($C$32&"-"&B37,Perfis!$A$3:$D$20,4,FALSE) -> 0.35 | D37: =C37*$C$33 -> 70
B38: HÍBRIDOS | C38: =VLOOKUP($C$32&"-"&B38,Perfis!$A$3:$D$20,4,FALSE) -> 0.08 | D38: =C38*$C$33 -> 16
B39: FOFs | C39: =VLOOKUP($C$32&"-"&B39,Perfis!$A$3:$D$20,4,FALSE) -> 0.05 | D39: =C39*$C$33 -> 10
B40: DESENVOLVIMENTO | C40: =VLOOKUP($C$32&"-"&B40,Perfis!$A$3:$D$20,4,FALSE) -> 0.1 | D40: =C40*$C$33 -> 20
B41: HOTELARIAS | C41: =VLOOKUP($C$32&"-"&B41,Perfis!$A$3:$D$20,4,FALSE) -> 0.1 | D41: =C41*$C$33 -> 20
B42: Total do aporte | C42: =SUM(C36:C41) -> 1 | D42: =SUM(D36:D41) -> 200
B60: Conferência dos dados
B61: Resultado das conferências | D61: =Conferências!B3 -> OK
B63: Preencha os campos amarelos. Os valores estão em reais (R$).
B64: Se aparecer REVISAR, abra a aba Conferências.
B65: Exercício com taxas constantes. Os resultados não garantem retorno.

Sheet Perfis
A2: Chave de busca | B2: Perfil | C2: Tipo de FII | D2: Percentual
A3: =B3&"-"&C3 -> Conservador-PAPEL | B3: Conservador | C3: PAPEL | D3: 0.3
A4: =B4&"-"&C4 -> Conservador-TIJOLO | B4: Conservador | C4: TIJOLO | D4: 0.5
A5: =B5&"-"&C5 -> Conservador-HÍBRIDOS | B5: Conservador | C5: HÍBRIDOS | D5: 0.1
A6: =B6&"-"&C6 -> Conservador-FOFs | B6: Conservador | C6: FOFs | D6: 0.1
A7: =B7&"-"&C7 -> Conservador-DESENVOLVIMENTO | B7: Conservador | C7: DESENVOLVIMENTO | D7: 0
A8: =B8&"-"&C8 -> Conservador-HOTELARIAS | B8: Conservador | C8: HOTELARIAS | D8: 0
A9: =B9&"-"&C9 -> Moderado-PAPEL | B9: Moderado | C9: PAPEL | D9: 0.32
A10: =B10&"-"&C10 -> Moderado-TIJOLO | B10: Moderado | C10: TIJOLO | D10: 0.35
A11: =B11&"-"&C11 -> Moderado-HÍBRIDOS | B11: Moderado | C11: HÍBRIDOS | D11: 0.08
A12: =B12&"-"&C12 -> Moderado-FOFs | B12: Moderado | C12: FOFs | D12: 0.05
A13: =B13&"-"&C13 -> Moderado-DESENVOLVIMENTO | B13: Moderado | C13: DESENVOLVIMENTO | D13: 0.1
A14: =B14&"-"&C14 -> Moderado-HOTELARIAS | B14: Moderado | C14: HOTELARIAS | D14: 0.1
... A20: =B20&"-"&C20 -> Agressivo-HOTELARIAS | B20: Agressivo | C20: HOTELARIAS | D20: 0.1
A23: Cada perfil deve somar 100%
B24: Perfil | C24: Soma | D24: Conferência
B25: Conservador | C25: =SUMIF($B$3:$B$20,B25,$D$3:$D$20) -> 1 | D25: =IF(ABS(C25-1)<0.00000001,"OK","REVISAR") -> OK
B26: Moderado | C26: =SUMIF($B$3:$B$20,B26,$D$3:$D$20) -> 1 | D26: =IF(ABS(C26-1)<0.00000001,"OK","REVISAR") -> OK
B27: Agressivo | C27: =SUMIF($B$3:$B$20,B27,$D$3:$D$20) -> 1 | D27: =IF(ABS(C27-1)<0.00000001,"OK","REVISAR") -> OK
A30: Percentuais do desafio DIO. Para testar outra divisão, edite as células amarelas e confira os totais acima.

Sheet Ajustes
A1: Ajustes e como usar
A4: Ajuste | B4: Valor | C4: Para que serve
A5: Percentual para sugerir o aporte | B5: 0.3 | C5: Usado na sugestão sobre o salário. O aporte mensal é preenchido por você.
A6: Meses por ano | B6: 12 | C6: Converte o prazo em anos para meses. Mantenha em 12.
A7: Capital inicial | B7: 0 | C7: Quanto você já tem investido ao começar a simulação.
A8: Momento do aporte | B8: 0 | C8: 0 = fim do mês; 1 = início do mês.
A9: Limite de prazo | B9: 50 | C9: A planilha aceita simulações de até 50 anos.
A10: Margem nas conferências | B10: 0.01 | C10: Aceita diferenças de até um centavo entre os cálculos. Mantenha em R$ 0,01.
A12: Por onde começar
A13: 1. Abra o Simulador e preencha os campos amarelos com salário, aporte, prazo e taxas mensais.
A14: 2. Escolha o perfil para ver a divisão do aporte. Se quiser mudar os percentuais, use a aba Perfis.
A15: 3. Compare os prazos e veja quanto do patrimônio vem do dinheiro investido e quanto vem dos rendimentos.
A16: 4. Confira o resultado no fim do painel. Se aparecer REVISAR, a aba Conferências indica o que precisa de ajuste.
A17: A taxa de acumulação projeta o patrimônio. A taxa de dividendos estima a renda mensal sobre o valor final.
A18: Trocar o perfil muda a divisão do aporte. Para comparar outro rendimento, altere também a taxa de acumulação.
A20: Antes de comparar os resultados
A21: Amarelo com texto azul: campos para preencher. Preto: fórmulas. Verde: fórmulas que consultam outra aba.
A22: A simulação usa taxas e aportes fixos. Não considera inflação, impostos, custos, variação no preço das cotas ou compra de cotas inteiras. Os perfis são exemplos do exercício, não recomendações de investimento.
A25: Sobre o projeto e as fórmulas
A26: Projeto do desafio de Excel da DIO, com taxas e perfis do exercício. A planilha não consulta cotações.
... A29: Validação de dados - Microsoft: https://support.microsoft.com/pt-br/excel/get-started/apply-data-validation-to-cells

Sheet Conferências
A1: Conferência dos cálculos
A3: Resultado geral | B3: =IF(COUNTIF(F6:F20,"REVISAR")=0,"OK","REVISAR") -> OK
A5: O que foi conferido | B5: Na planilha | C5: Esperado | D5: Diferença | E5: Margem | F5: Resultado
A6: Soma do perfil Conservador | B6: =Perfis!C25 -> 1 | C6: =1 -> 1 | D6: =B6-C6 -> 0 | E6: 1e-08 | F6: =IFERROR(IF(ABS(D6)<=E6,"OK","REVISAR"),"REVISAR") -> OK
A7: Soma do perfil Moderado | B7: =Perfis!C26 -> 1 | C7: =1 -> 1 | D7: =B7-C7 -> 0 | E7: 1e-08 | F7: =IFERROR(IF(ABS(D7)<=E7,"OK","REVISAR"),"REVISAR") -> OK
A8: Soma do perfil Agressivo | B8: =Perfis!C27 -> 1 | C8: =1 -> 1 | D8: =B8-C8 -> 0 | E8: 1e-08 | F8: =IFERROR(IF(ABS(D8)<=E8,"OK","REVISAR"),"REVISAR") -> OK
A9: Percentuais do perfil escolhido | B9: =Simulador!C42 -> 1 | C9: =1 -> 1 | D9: =B9-C9 -> 0 | E9: 1e-08 | F9: =IFERROR(IF(ABS(D9)<=E9,"OK","REVISAR"),"REVISAR") -> OK
A10: Distribuição do aporte mensal | B10: =Simulador!D42 -> 200 | C10: =aporte -> 200 | D10: =B10-C10 -> 0 | E10: =tolerancia -> 0.01 | F10: =IFERROR(IF(ABS(D10)<=E10,"OK","REVISAR"),"REVISAR") -> OK
A11: Patrimônio calculado de outra forma | B11: =patrimonio -> 16755.383 | C11: =IF(taxa_mensal=0,capital_inicial+aporte*qtd_anos*meses_ano,capital_inicial*(1+taxa_mensal)^(qtd_anos*meses_ano)+aporte*((1+taxa_mensal)^(qtd_anos*meses_ano)-1)/taxa_mensal*(1+taxa_mensal*momento_aporte)) -> 16755.383 | D11: =B11-C11 -> 0 | E11: =tolerancia -> 0.01 | F11: =IFERROR(IF(ABS(D11)<=E11,"OK","REVISAR"),"REVISAR") -> OK
A12: Capital inicial e aportes | B12: =Simulador!D29 -> 12000 | C12: =capital_inicial+aporte*qtd_anos*meses_ano -> 12000 | D12: =B12-C12 -> 0 | E12: =tolerancia -> 0.01 | F12: =IFERROR(IF(ABS(D12)<=E12,"OK","REVISAR"),"REVISAR") -> OK
A13: Investido + rendimentos = patrimônio | B13: =patrimonio -> 16755.383 | C13: =SUM(Simulador!D29:D30) -> 16755.383 | D13: =B13-C13 -> 0 | E13: =tolerancia -> 0.01 | F13: =IFERROR(IF(ABS(D13)<=E13,"OK","REVISAR"),"REVISAR") -> OK
A14: Dividendo mensal estimado | B14: =Simulador!D21 -> 100.5323 | C14: =patrimonio*rendimento_carteira -> 100.5323 | D14: =B14-C14 -> 0 | E14: =tolerancia -> 0.01 | F14: =IFERROR(IF(ABS(D14)<=E14,"OK","REVISAR"),"REVISAR") -> OK
A15: Campos numéricos preenchidos | B15: =COUNT(Simulador!D12:D13,Simulador!D17:D19,Ajustes!B5:B10) -> 11 | C15: =11 -> 11 | D15: =B15-C15 -> 0 | E15: =0 -> 0 | F15: =IFERROR(IF(ABS(D15)<=E15,"OK","REVISAR"),"REVISAR") -> OK
A16: Perfil escolhido na lista | B16: =COUNTIF(perfis,Simulador!C32) -> 1 | C16: =1 -> 1 | D16: =B16-C16 -> 0 | E16: =0 -> 0 | F16: =IFERROR(IF(ABS(D16)<=E16,"OK","REVISAR"),"REVISAR") -> OK
A17: Prazo em anos inteiros | B17: =IF(AND(qtd_anos>=0,qtd_anos<=limite_anos,MOD(qtd_anos,1)=0,limite_anos<=50,limite_anos>=0),1,0) -> 1 | C17: =1 -> 1 | D17: =B17-C17 -> 0 | E17: =0 -> 0 | F17: =IFERROR(IF(ABS(D17)<=E17,"OK","REVISAR"),"REVISAR") -> OK
A18: Taxas dentro dos limites | B18: =IF(AND(taxa_mensal>=-0.99,taxa_mensal<=1,rendimento_carteira>=0,rendimento_carteira<=1),1,0) -> 1 | C18: =1 -> 1 | D18: =B18-C18 -> 0 | E18: =0 -> 0 | F18: =IFERROR(IF(ABS(D18)<=E18,"OK","REVISAR"),"REVISAR") -> OK
A19: Valores e ajustes dentro dos limites | B19: =IF(AND(salario>=0,salario<=100000000,aporte>=0,aporte<=1000000,capital_inicial>=0,capital_inicial<=100000000,percentual_sugerido>=0,percentual_sugerido<=1,meses_ano=12,OR(momento_aporte=0,momento_aporte=1),tolerancia=0.01),1,0) -> 1 | C19: =1 -> 1 | D19: =B19-C19 -> 0 | E19: =0 -> 0 | F19: =IFERROR(IF(ABS(D19)<=E19,"OK","REVISAR"),"REVISAR") -> OK
A20: Percentuais entre 0% e 100% | B20: =IF(AND(COUNT(Perfis!D3:D20)=18,MIN(Perfis!D3:D20)>=0,MAX(Perfis!D3:D20)<=1),1,0) -> 1 | C20: =1 -> 1 | D20: =B20-C20 -> 0 | E20: =0 -> 0 | F20: =IFERROR(IF(ABS(D20)<=E20,"OK","REVISAR"),"REVISAR") -> OK
A23: Se alguma linha mostrar REVISAR, confira os valores em Simulador, Perfis e Ajustes. A coluna Margem mostra a diferença aceita em cada conta. Um resultado OK confirma as contas, não o retorno do investimento.
